iracema/__init__.py
iracema/aggregation.py
iracema/features.py
iracema/harmonics.py
iracema/pitch.py
iracema/plot.py
iracema/run.py
iracema/spectral.py
iracema/assets/audio/Click.wav
iracema/core/__init__.py
iracema/core/audio.py
iracema/core/point.py
iracema/core/segment.py
iracema/core/timeseries.py
iracema/extra/__init__.py
iracema/extra/jupyterutil.py
iracema/extra/synth.py
iracema/io/__init__.py
iracema/io/audiofile.py
iracema/io/player.py
iracema/segmentation/__init__.py
iracema/segmentation/clari-onsets.h5
iracema/segmentation/evaluation.py
iracema/segmentation/note_envelope.py
iracema/segmentation/odfs.py
iracema/segmentation/onsets.py
iracema/segmentation/util.py
iracema/util/__init__.py
iracema/util/config.py
iracema/util/conversion.py
iracema/util/dsp.py
iracema/util/ml.py
iracema/util/windowing.py
iracema-0.2.1.dist-info/LICENSE
iracema-0.2.1.dist-info/METADATA
iracema-0.2.1.dist-info/WHEEL
iracema-0.2.1.dist-info/top_level.txt
iracema-0.2.1.dist-info/RECORD
