Metadata-Version: 2.1
Name: iracema
Version: 0.2.1
Summary: Audio Content Analysis for Research on Musical Expressiveness and Individuality
Home-page: http://github.com/cegeme/iracema
Author: Tairone Magalhães
Author-email: taironemagalhaes@gmail.com
License: UNKNOWN
Platform: UNKNOWN
Classifier: Development Status :: 3 - Alpha
Classifier: Intended Audience :: Developers
Classifier: Intended Audience :: Science/Research
Classifier: Programming Language :: Python :: 3
Classifier: License :: OSI Approved :: GNU General Public License v3 (GPLv3)
Classifier: Topic :: Multimedia :: Sound/Audio :: Analysis
Classifier: Topic :: Scientific/Engineering :: Information Analysis
Classifier: Topic :: Software Development :: Libraries
Requires-Dist: numpy (>=1.18.5)
Requires-Dist: scipy (>=1.6.1)
Requires-Dist: sounddevice (>=0.3.12)
Requires-Dist: audioread (>=2.1.8)
Requires-Dist: matplotlib (==3.3.4)
Requires-Dist: resampy (==0.2.2)
Requires-Dist: Deprecated (==1.2.10)
Requires-Dist: librosa (==0.8.0)
Requires-Dist: w3lib (==1.22.0)
Requires-Dist: tensorflow (==2.3.2)
